{
  "examType": "agniveer_army",
  "district": "mock",
  "year": 3,
  "name": "Agniveer Army Mock Paper 3",
  "sections": [
    {
      "id": "gk",
      "questions": [
        { "q": "16. भारत का दक्षिणतम बिंदु कौन-सा है?", "options": ["कन्याकुमारी", "इंदिरा पॉइंट", "इंदिरा कोल", "कीबिथू"], "answer": 1 },
        { "q": "17. जलियांवाला बाग हत्याकांड कब हुआ था?", "options": ["1917", "1918", "1919", "1920"], "answer": 2 },
        { "q": "18. हीराकुंड बांध किस नदी पर बना है?", "options": ["गंगा", "नर्मदा", "महानदी", "गोदावरी"], "answer": 2 },
        { "q": "19. 'सत्यमेव जयते' कहाँ से लिया गया है?", "options": ["ऋग्वेद", "रामायण", "मुण्डकोपनिषद्", "महाभारत"], "answer": 2 },
        { "q": "20. गरबा किस राज्य का लोक नृत्य है?", "options": ["महाराष्ट्र", "राजस्थान", "गुजरात", "पंजाब"], "answer": 2 },
        { "q": "21. भारत की सबसे लंबी नदी कौन-सी है?", "options": ["ब्रह्मपुत्र", "गंगा", "गोदावरी", "सिंधु"], "answer": 1 },
        { "q": "22. शिक्षक दिवस किसकी याद में मनाया जाता है?", "options": ["जवाहरलाल नेहरू", "महात्मा गांधी", "डॉ. सर्वपल्ली राधाकृष्णन", "डॉ. ए.पी.जे. अब्दुल कलाम"], "answer": 2 },
        { "q": "23. काजीरंगा राष्ट्रीय उद्यान किसके लिए प्रसिद्ध है?", "options": ["शेर", "बाघ", "हाथी", "एक सींग वाला गेंडा"], "answer": 3 },
        { "q": "24. थार मरुस्थल किस राज्य में स्थित है?", "options": ["गुजरात", "हरियाणा", "राजस्थान", "पंजाब"], "answer": 2 },
        { "q": "25. लोकसभा अध्यक्ष का चुनाव कौन करता है?", "options": ["राष्ट्रपति", "प्रधानमंत्री", "लोकसभा के सदस्य", "राज्यसभा के सदस्य"], "answer": 2 },
        { "q": "26. भारत का मैनचेस्टर किसे कहा जाता है?", "options": ["मुंबई", "अहमदाबाद", "कानपुर", "कोयंबटूर"], "answer": 1 },
        { "q": "27. स्वर्ण मंदिर कहाँ स्थित है?", "options": ["दिल्ली", "अमृतसर", "चंडीगढ़", "पटियाला"], "answer": 1 },
        { "q": "28. 'विंग्स ऑफ फायर' किसकी आत्मकथा है?", "options": ["सचिन तेंदुलकर", "महात्मा गांधी", "जवाहरलाल नेहरू", "डॉ. ए.पी.जे. अब्दुल कलाम"], "answer": 3 },
        { "q": "29. गोवा की राजधानी क्या है?", "options": ["पणजी", "इंफाल", "शिलॉन्ग", "गंगटोक"], "answer": 0 },
        { "q": "30. आगा खां कप किस खेल से संबंधित है?", "options": ["क्रिकेट", "फुटबॉल", "हॉकी", "टेनिस"], "answer": 2 }
      ]
    },
    {
      "id": "science",
      "questions": [
        { "q": "1. पेंसिल में प्रयुक्त होने वाला काला पदार्थ क्या है?", "options": ["लोहा", "ग्रेफाइट", "जस्ता", "मैग्नीज"], "answer": 1 },
        { "q": "2. शुद्ध जल का pH मान कितना होता है?", "options": ["0", "1", "7", "14"], "answer": 2 },
        { "q": "3. मनुष्य की आंख में प्रतिबिंब कहाँ बनता है?", "options": ["पुतली", "रेटिना", "कॉर्निया", "आइरिस"], "answer": 1 },
        { "q": "4. लाफिंग गैस (हंसाने वाली गैस) का रासायनिक नाम क्या है?", "options": ["नाइट्रिक ऑक्साइड", "नाइट्रस ऑक्साइड", "नाइट्रोजन", "क्लोरीन"], "answer": 1 },
        { "q": "5. गुरुत्वाकर्षण का नियम किसने दिया था?", "options": ["गैलीलियो", "आइंस्टीन", "न्यूटन", "फैराडे"], "answer": 2 },
        { "q": "6. मनुष्य के हृदय में कितने कोष्ठक (Chambers) होते हैं?", "options": ["2", "3", "4", "1"], "answer": 2 },
        { "q": "7. ओजोन परत हमें किन किरणों से बचाती है?", "options": ["एक्स-रे", "अवरक्त किरणें", "पराबैंगनी किरणें", "गामा किरणें"], "answer": 2 },
        { "q": "8. दूध की शुद्धता किस यंत्र से मापी जाती है?", "options": ["हाइड्रोमीटर", "लैक्टोमीटर", "बैरोमीटर", "हाइग्रोमीटर"], "answer": 1 },
        { "q": "9. विटामिन सी की कमी से होने वाला रोग है:", "options": ["बेरी-बेरी", "रतौंधी", "एनीमिया", "स्कर्वी"], "answer": 3 },
        { "q": "10. वायु क्या है?", "options": ["तत्व", "यौगिक", "मिश्रण", "कोई नहीं"], "answer": 2 },
        { "q": "11. 'कार्य' का मात्रक क्या है?", "options": ["न्यूटन", "जूल", "वाट", "पास्कल"], "answer": 1 },
        { "q": "12. पेनिसिलिन की खोज किसने की थी?", "options": ["लुई पाश्चर", "एडवर्ड जेनर", "अलेक्जेंडर फ्लेमिंग", "वाट्सन"], "answer": 2 },
        { "q": "13. रक्त का थक्का जमाने में कौन-सा विटामिन सहायक है?", "options": ["विटामिन ए", "विटामिन सी", "विटामिन के", "विटामिन ई"], "answer": 2 },
        { "q": "14. शुष्क बर्फ (Dry Ice) किसे कहते हैं?", "options": ["ठोस नाइट्रोजन", "ठोस कार्बन डाइऑक्साइड", "ठोस हाइड्रोजन", "कोई नहीं"], "answer": 1 },
        { "q": "15. मनुष्य के शरीर का सामान्य तापमान कितना होता है?", "options": ["37°C", "98.4°C", "310°C", "25°C"], "answer": 0 }
      ]
    },
    {
      "id": "math",
      "questions": [
        { "q": "31. ₹800 का 5% कितना होगा?", "options": ["40", "80", "160", "20"], "answer": 0 },
        { "q": "32. 4, 8, 12, 16 का औसत क्या होगा?", "options": ["8", "10", "12", "14"], "answer": 1 },
        { "q": "33. एक वर्ग का परिमाप 40 सेमी है। उसका क्षेत्रफल क्या होगा?", "options": ["10 वर्ग सेमी", "40 वर्ग सेमी", "100 वर्ग सेमी", "1600 वर्ग सेमी"], "answer": 2 },
        { "q": "34. यदि 3x = 27, तो x का मान क्या है?", "options": ["3", "6", "9", "12"], "answer": 2 },
        { "q": "35. ₹1200 की वस्तु पर 20% की छूट देने पर विक्रय मूल्य क्या होगा?", "options": ["₹960", "₹1000", "₹1080", "₹1140"], "answer": 0 },
        { "q": "36. 1/2 + 1/4 का मान क्या होगा?", "options": ["1/6", "3/4", "1/8", "2/6"], "answer": 1 },
        { "q": "37. वृत्त की सबसे बड़ी जीवा (Chord) क्या कहलाती है?", "options": ["त्रिज्या", "चाप", "व्यास", "परिधि"], "answer": 2 },
        { "q": "38. प्रथम 10 प्राकृत संख्याओं का योग क्या होगा?", "options": ["45", "50", "55", "60"], "answer": 2 },
        { "q": "39. 25 : 5 :: 100 : ?", "options": ["10", "20", "25", "50"], "answer": 1 },
        { "q": "40. यदि क्रय मूल्य ₹400 और लाभ ₹40 हो, तो लाभ प्रतिशत बताएं:", "options": ["5%", "10%", "15%", "20%"], "answer": 1 },
        { "q": "41. एक कार 60 किमी/घंटा की चाल से 3 घंटे में कितनी दूरी तय करेगी?", "options": ["120 किमी", "150 किमी", "180 किमी", "200 किमी"], "answer": 2 },
        { "q": "42. 0.25 को भिन्न में बदलें:", "options": ["1/2", "1/4", "1/5", "1/10"], "answer": 1 },
        { "q": "43. बेलन के वक्र पृष्ठ का क्षेत्रफल क्या है?", "options": ["πr²", "2πrh", "πrl", "2πr²"], "answer": 1 },
        { "q": "44. (10 + 5) × 2 का मान क्या होगा?", "options": ["20", "25", "30", "35"], "answer": 2 },
        { "q": "45. x² - 4 = 0 को हल करें:", "options": ["x=2", "x=4", "x=±2", "x=±4"], "answer": 2 }
      ]
    },
    {
      "id": "reasoning",
      "questions": [
        { "q": "46. श्रृंखला पूर्ण करें: 5, 10, 20, 40, ?", "options": ["60", "80", "100", "120"], "answer": 1 },
        { "q": "47. फल : आम :: सब्जी : ?", "options": ["सेब", "केला", "आलू", "गुलाब"], "answer": 2 },
        { "q": "48. यदि 'BOY' का कोड 'CPZ' है, तो 'GIRL' का कोड क्या होगा?", "options": ["HJSK", "HJSM", "HISM", "HISM"], "answer": 1 },
        { "q": "49. विषम चुनें:", "options": ["गाय", "भैंस", "बकरी", "शेर"], "answer": 3 },
        { "q": "50. सुबह के समय सूरज की ओर पीठ करके चलने पर आपकी परछाई किस ओर होगी?", "options": ["सामने", "पीछे", "बाएं", "दाएं"], "answer": 0 }
      ]
    }
  ]
}
